CHANGES.txt
DEPENDENCES.txt
README.txt
setup.py
src/ng/__init__.py
src/ng.content.article.egg-info/PKG-INFO
src/ng.content.article.egg-info/SOURCES.txt
src/ng.content.article.egg-info/dependency_links.txt
src/ng.content.article.egg-info/namespace_packages.txt
src/ng.content.article.egg-info/not-zip-safe
src/ng.content.article.egg-info/requires.txt
src/ng.content.article.egg-info/top_level.txt
src/ng/content/__init__.py
src/ng/content/article/__init__.py
src/ng/content/article/configure.zcml
src/ng/content/article/interfaces.py
src/ng/content/article/ng.content.article.txt
src/ng/content/article/adapter/__init__.py
src/ng/content/article/adapter/configure.zcml
src/ng/content/article/adapter/containeradapter.py
src/ng/content/article/article/__init__.py
src/ng/content/article/article/article.py
src/ng/content/article/article/article.txt
src/ng/content/article/article/articlelink.py
src/ng/content/article/article/configure.zcml
src/ng/content/article/article/interfaces.py
src/ng/content/article/article/browser/__init__.py
src/ng/content/article/article/browser/article.pt
src/ng/content/article/article/browser/articleshort.pt
src/ng/content/article/article/browser/configure.zcml
src/ng/content/article/browser/__init__.py
src/ng/content/article/browser/configure.zcml
src/ng/content/article/browser/export.py
src/ng/content/article/division/__init__.py
src/ng/content/article/division/configure.zcml
src/ng/content/article/division/division.py
src/ng/content/article/division/division.txt
src/ng/content/article/division/interfaces.py
src/ng/content/article/division/browser/__init__.py
src/ng/content/article/division/browser/configure.zcml
src/ng/content/article/division/browser/division.pt
src/ng/content/article/division/browser/divisionshort.pt
src/ng/content/article/etc/contentobjects-configure.zcml
src/ng/content/article/ftp/__init__.py
src/ng/content/article/ftp/article2attributediradapter.py
src/ng/content/article/ftp/configure.zcml
src/ng/content/article/ftp/directoryfactory.py
src/ng/content/article/ftp/division2attributediradapter.py
src/ng/content/article/ftp/remotearticle2attributediradapter.py
src/ng/content/article/maincontainer/__init__.py
src/ng/content/article/maincontainer/configure.zcml
src/ng/content/article/maincontainer/interfaces.py
