Metadata-Version: 1.0
Name: ng.content.article
Version: 1.0.7
Summary: Content-object Article used to represent site text content
Home-page: http://www.dreambot.ru/product/DreamBotSite/ng.content.article
Author: Andrey Orlov
Author-email: dbdt@dreambot.ru
License: GPL v2.1
Platform: UNKNOWN
Classifier: Environment :: Web Environment
Classifier: Intended Audience :: Developers
Classifier: License :: OSI Approved :: GNU General Public License (GPL)
Classifier: Programming Language :: Python
Classifier: Operating System :: OS Independent
Classifier: Topic :: Internet :: WWW/HTTP
Classifier: Framework :: Zope3
